{"cameraMode":{"drawMode":0,"name":"Shaded","section":"Shading Mode"},"sceneLighting":true,"audioPlay":false,"sceneViewState":{"m_AlwaysRefresh":false,"showFog":false,"showSkybox":false,"showFlares":true,"showImageEffects":true,"showParticleSystems":true,"showVisualEffectGraphs":true,"m_FxEnabled":true},"in2DMode":false,"pivot":{"x":0.0,"y":2.0,"z":0.0},"rotation":{"x":-0.35396629571914675,"y":-0.0022479381877928974,"z":0.0008505650330334902,"w":-0.9352569580078125},"size":23.495267868041993,"orthographic":false}